robclient/__init__.py
robclient/config.py
robclient/route.py
robclient/table.py
robclient/version.py
robclient/cli/__init__.py
robclient/cli/base.py
robclient/cli/benchmark.py
robclient/cli/files.py
robclient/cli/run.py
robclient/cli/submission.py
robclient/cli/user.py
rob_client-0.2.0.dist-info/LICENSE
rob_client-0.2.0.dist-info/METADATA
rob_client-0.2.0.dist-info/WHEEL
rob_client-0.2.0.dist-info/entry_points.txt
rob_client-0.2.0.dist-info/top_level.txt
rob_client-0.2.0.dist-info/RECORD
