Metadata-Version: 2.1
Name: rob-client
Version: 0.2.0
Summary: Reproducible Open Benchmarks - Command Line Client
Home-page: https://github.com/scailfin/rob-client
Author: Heiko Mueller
Author-email: heiko.muller@gmail.com
License: MIT
Keywords: reproducibility benchmarks data-analysis
Platform: UNKNOWN
Classifier: License :: OSI Approved :: MIT License
Classifier: Operating System :: OS Independent
Classifier: Programming Language :: Python :: 2
Classifier: Programming Language :: Python :: 2.7
Classifier: Programming Language :: Python :: 3
Classifier: Programming Language :: Python :: 3.6
Classifier: Programming Language :: Python :: 3.7
Classifier: Programming Language :: Python
Requires-Dist: future
Requires-Dist: Click
Requires-Dist: requests
Requires-Dist: flowserv-core (>=0.2.0)
Provides-Extra: docs
Requires-Dist: Sphinx ; extra == 'docs'
Requires-Dist: sphinx-rtd-theme ; extra == 'docs'
Provides-Extra: tests
Requires-Dist: coverage (>=4.0) ; extra == 'tests'
Requires-Dist: pytest ; extra == 'tests'
Requires-Dist: pytest-cov ; extra == 'tests'
Requires-Dist: tox ; extra == 'tests'
